{
  "question": "Welche der folgenden Anweisungen in Python führt zu einem Syntaxfehler?",
  "answers": [
    { "answer": "x = 10", "correct": false },
    { "answer": "print(x)", "correct": false },
    { "answer": "if x > 10:", "correct": false },
    { "answer": "6 = x", "correct": true },
    { "answer": "x == x + 1", "correct": false },
    { "answer": "x += 1", "correct": false }
  ],
  "description": "In Python führt der Versuch, einem Literal einen Wert zuzuweisen, zu einem Syntaxfehler, da Literale keine Variablen sind und somit keinen Wert zugewiesen bekommen können.",
  "score": 2
}
